obj_update.py
dj_obj_update-0.6.0.dist-info/LICENSE
dj_obj_update-0.6.0.dist-info/WHEEL
dj_obj_update-0.6.0.dist-info/METADATA
dj_obj_update-0.6.0.dist-info/RECORD
