Metadata-Version: 2.1
Name: dj-obj-update
Version: 0.6.0
Summary: `dj-obj-update` helps you update an object but only saves if something changed.
Home-page: https://github.com/crccheck/obj_update
License: UNKNOWN
Author: Chris Chang
Author-email: c@crccheck.com
Requires-Python: >=3.4
Classifier: Development Status :: 4 - Beta
Classifier: Framework :: Django
Classifier: Intended Audience :: Developers
Classifier: License :: OSI Approved :: Apache Software License
Classifier: Operating System :: OS Independent
Classifier: Programming Language :: Python :: 3
